sajilo_orm/__init__.py
sajilo_orm/exceptions.py
sajilo_orm/field.py
sajilo_orm/manager.py
sajilo_orm/models.py
sajilo_orm/query_manager.py
sajilo_orm/settings.py
sajilo_orm-0.0.6.dist-info/LICENSE.md
sajilo_orm-0.0.6.dist-info/METADATA
sajilo_orm-0.0.6.dist-info/WHEEL
sajilo_orm-0.0.6.dist-info/top_level.txt
sajilo_orm-0.0.6.dist-info/RECORD
