Metadata-Version: 2.1
Name: sajilo-orm
Version: 0.0.6
Summary: Sarai Sajilo lightweight ORM inspired by Django ORM with nepali twist
Home-page: https://github.com/learningnoobi/sajilo-orm
Author: learningnoobi (Bishal Rai)
Author-email: fanime492@gmail.com
License: MIT
Classifier: Programming Language :: Python :: 3
Classifier: Programming Language :: Python :: 3.6
Classifier: Programming Language :: Python :: 3.7
Classifier: License :: OSI Approved :: GNU General Public License v3 (GPLv3)
Classifier: Operating System :: OS Independent
Requires-Python: >=3.6
License-File: LICENSE.md
Requires-Dist: colorama (~=0.4.4)
Requires-Dist: iniconfig (~=1.1.1)
Requires-Dist: mypy-extensions (~=0.4.3)
Requires-Dist: packaging (~=21.3)
Requires-Dist: pathspec (~=0.9.0)
Requires-Dist: platformdirs (~=2.5.2)
Requires-Dist: pluggy (~=1.0.0)
Requires-Dist: psycopg2-binary (~=2.9.3)
Requires-Dist: py (~=1.11.0)
Requires-Dist: pyparsing (~=3.0.8)
Requires-Dist: tomli (~=2.0.1)
Provides-Extra: dev
Requires-Dist: coverage (==6.3.2) ; extra == 'dev'
Requires-Dist: pytest (==7.1.2) ; extra == 'dev'
